beamgis/__init__.py
beamgis/beamgis.py
beamgis/common.py
beamgis/foliumap.py
beamgis-0.0.3.dist-info/licenses/LICENSE
beamgis-0.0.3.dist-info/METADATA
beamgis-0.0.3.dist-info/WHEEL
beamgis-0.0.3.dist-info/entry_points.txt
beamgis-0.0.3.dist-info/top_level.txt
beamgis-0.0.3.dist-info/RECORD
