Metadata-Version: 2.4
Name: beamgis
Version: 0.0.3
Summary: A python package for geospatial analysis and mapping
Author-email: Emmanuel Afriyie <afriyiemma@gmail.com>
License: MIT License
Project-URL: Homepage, https://github.com/eafriyie28/beamgis
Keywords: beamgis
Classifier: Intended Audience :: Developers
Classifier: License :: OSI Approved :: MIT License
Classifier: Natural Language :: English
Classifier: Programming Language :: Python :: 3.8
Classifier: Programming Language :: Python :: 3.9
Classifier: Programming Language :: Python :: 3.10
Classifier: Programming Language :: Python :: 3.11
Classifier: Programming Language :: Python :: 3.12
Requires-Python: >=3.8
License-File: LICENSE
Requires-Dist: folium
Requires-Dist: geopandas
Requires-Dist: ipyleaflet
Requires-Dist: numpy
Provides-Extra: all
Requires-Dist: beamgis[extra]; extra == "all"
Provides-Extra: extra
Requires-Dist: pandas; extra == "extra"
Dynamic: license-file
